weblogin/Makefile
weblogin/__init__.py
weblogin/init.nw
weblogin/kth.nw
weblogin/kth.py
weblogin/ladok.nw
weblogin/ladok.py
weblogin/seamlessaccess.nw
weblogin/seamlessaccess.py
weblogin-1.13.dist-info/LICENSE
weblogin-1.13.dist-info/METADATA
weblogin-1.13.dist-info/WHEEL
weblogin-1.13.dist-info/RECORD
