Metadata-Version: 2.3
Name: weblogin
Version: 1.13
Summary: Automates logging into web UIs to access unofficial APIs
License: MIT
Author: Daniel Bosk
Author-email: dbosk@kth.se
Requires-Python: >=3.8,<4.0
Classifier: License :: OSI Approved :: MIT License
Classifier: Programming Language :: Python :: 3
Classifier: Programming Language :: Python :: 3.8
Classifier: Programming Language :: Python :: 3.9
Classifier: Programming Language :: Python :: 3.10
Classifier: Programming Language :: Python :: 3.11
Classifier: Programming Language :: Python :: 3.12
Classifier: Programming Language :: Python :: 3.13
Requires-Dist: lxml (>=5.3.0,<6.0.0)
Requires-Dist: requests (>=2.28.1,<3.0.0)
Project-URL: Bug Tracker, https://github.com/dbosk/weblogin/issues
Project-URL: Repository, https://github.com/dbosk/weblogin
Project-URL: Releases, https://github.com/dbosk/weblogin/releases
